topsisNaman/102083045.py
topsisNaman/__init__.py
Topsis_Naman_102083045-1.0.0.dist-info/METADATA
Topsis_Naman_102083045-1.0.0.dist-info/WHEEL
Topsis_Naman_102083045-1.0.0.dist-info/top_level.txt
Topsis_Naman_102083045-1.0.0.dist-info/RECORD
