Metadata-Version: 2.1
Name: Topsis-Naman-102083045
Version: 1.0.0
Summary: Topsis
Home-page: https://github.com/
Author: Naman Garg
Author-email: ngarg4_be19@thapar.edu
License: MIT
Platform: UNKNOWN
Classifier: License :: OSI Approved :: MIT License
Classifier: Programming Language :: Python :: 3.6
Classifier: Programming Language :: Python :: 3.7
Classifier: Programming Language :: Python :: 3.8
